avcv/__init__.py
avcv/_imports.py
avcv/_modidx.py
avcv/_nbdev.py
avcv/all.py
avcv/cli.py
avcv/coco.py
avcv/debug.py
avcv/dist_utils.py
avcv/lazy_modules.py
avcv/process.py
avcv/utils.py
avcv/visualize.py
avcv-0.0.54.dist-info/LICENSE
avcv-0.0.54.dist-info/METADATA
avcv-0.0.54.dist-info/WHEEL
avcv-0.0.54.dist-info/entry_points.txt
avcv-0.0.54.dist-info/top_level.txt
avcv-0.0.54.dist-info/RECORD
