Metadata-Version: 2.1
Name: avcv
Version: 0.0.54
Summary: Python package utils for computer vision
Home-page: https://github.com/anhvth/avcv/tree/nbdev-convert/
Author: Hai Anh
Author-email: anhvth.226@gmail.com
License: Apache Software License 2.0
Keywords: computer vision
Classifier: Development Status :: 3 - Alpha
Classifier: Intended Audience :: Developers
Classifier: Natural Language :: English
Classifier: Programming Language :: Python :: 3.6
Classifier: Programming Language :: Python :: 3.7
Classifier: Programming Language :: Python :: 3.8
Classifier: License :: OSI Approved :: Apache Software License
Requires-Python: >=3.6
License-File: LICENSE
Requires-Dist: tqdm
Requires-Dist: xxhash
Requires-Dist: matplotlib
Requires-Dist: scikit-learn
Requires-Dist: scikit-image
Requires-Dist: ipdb
Requires-Dist: imutils
Requires-Dist: opencv-python
Requires-Dist: pandas
Requires-Dist: fastcore
Requires-Dist: openpyxl
Requires-Dist: loguru
Requires-Dist: pycocotools
Requires-Dist: lazy-module
Requires-Dist: mmcv (==1.7)
